{"data":[{"code":"32.09.24","name":"Arjawinangun"},{"code":"32.09.10","name":"Astanajapura"},{"code":"32.09.05","name":"Babakan"},{"code":"32.09.13","name":"Beber"},{"code":"32.09.02","name":"Ciledug"},{"code":"32.09.26","name":"Ciwaringin"},{"code":"32.09.31","name":"Depok"},{"code":"32.09.16","name":"Dukupuntang"},{"code":"32.09.30","name":"Gebang"},{"code":"32.09.28","name":"Gegesik"},{"code":"32.09.37","name":"Gempol"},{"code":"32.09.38","name":"Greged"},{"code":"32.09.21","name":"Gunung Jati"},{"code":"32.09.40","name":"Jamblang"},{"code":"32.09.29","name":"Kaliwedi"},{"code":"32.09.06","name":"Karangsembung"},{"code":"32.09.34","name":"Karangwareng"},{"code":"32.09.20","name":"Kedawung"},{"code":"32.09.22","name":"Kepetakan"},{"code":"32.09.23","name":"Klangenan"},{"code":"32.09.07","name":"Lemahabang"},{"code":"32.09.03","name":"Losari"},{"code":"32.09.12","name":"Mundu"},{"code":"32.09.04","name":"Pabedilan"},{"code":"32.09.33","name":"Pabuaran"},{"code":"32.09.17","name":"Palimanan"},{"code":"32.09.11","name":"Pangenan"},{"code":"32.09.25","name":"Panguragan"},{"code":"32.09.32","name":"Pasaleman"},{"code":"32.09.36","name":"Plered"},{"code":"32.09.18","name":"Plumbon"},{"code":"32.09.09","name":"Sedong"},{"code":"32.09.15","name":"Sumber"},{"code":"32.09.39","name":"Suranenggala"},{"code":"32.09.27","name":"Susukan"},{"code":"32.09.08","name":"Susukan Lebak"},{"code":"32.09.14","name":"Talun"},{"code":"32.09.35","name":"Tengah Tani"},{"code":"32.09.01","name":"Waled"},{"code":"32.09.19","name":"Weru"}],"meta":{"administrative_area_level":3,"updated_at":"2025-07-04"}}