{"data":[{"code":"16.04.21","name":"Gumay Talang"},{"code":"16.04.25","name":"Gumay Ulu"},{"code":"16.04.06","name":"Jarai"},{"code":"16.04.19","name":"Kikim Barat"},{"code":"16.04.16","name":"Kikim Selatan"},{"code":"16.04.18","name":"Kikim Tengah"},{"code":"16.04.17","name":"Kikim Timur"},{"code":"16.04.07","name":"Kota Agung"},{"code":"16.04.10","name":"Lahat"},{"code":"16.04.31","name":"Lahat Selatan"},{"code":"16.04.09","name":"Merapi Barat"},{"code":"16.04.26","name":"Merapi Selatan"},{"code":"16.04.23","name":"Merapi Timur"},{"code":"16.04.28","name":"Muarapayang"},{"code":"16.04.30","name":"Mulak Sebingkai"},{"code":"16.04.15","name":"Mulak Ulu"},{"code":"16.04.22","name":"Pagar Gunung"},{"code":"16.04.12","name":"Pajar Bulan"},{"code":"16.04.20","name":"Pseksu"},{"code":"16.04.08","name":"Pulau Pinang"},{"code":"16.04.29","name":"Sukamerindu"},{"code":"16.04.24","name":"Tanjung Sakti Pumi"},{"code":"16.04.01","name":"Tanjungsakti Pumu"},{"code":"16.04.27","name":"Tanjungtebat"}],"meta":{"administrative_area_level":3,"updated_at":"2025-07-04"}}