{"data":[{"code":"74.02.10","name":"Abuki"},{"code":"74.02.28","name":"Amonggedo"},{"code":"74.02.24","name":"Anggaberi"},{"code":"74.02.40","name":"Anggalomoare"},{"code":"74.02.31","name":"Asinua"},{"code":"74.02.20","name":"Besulutu"},{"code":"74.02.21","name":"Bondoala"},{"code":"74.02.33","name":"Kapoiala"},{"code":"74.02.32","name":"Konawe"},{"code":"74.02.36","name":"Lalonggasumeeto"},{"code":"74.02.01","name":"Lambuya"},{"code":"74.02.16","name":"Latoma"},{"code":"74.02.25","name":"Meluhu"},{"code":"74.02.39","name":"Morosi"},{"code":"74.02.37","name":"Onembute"},{"code":"74.02.38","name":"Padangguni"},{"code":"74.02.04","name":"Pondidaha"},{"code":"74.02.17","name":"Puriala"},{"code":"74.02.23","name":"Routa"},{"code":"74.02.05","name":"Sampara"},{"code":"74.02.11","name":"Soropia"},{"code":"74.02.15","name":"Tongauna"},{"code":"74.02.42","name":"Tongauna Utara"},{"code":"74.02.18","name":"Uepai"},{"code":"74.02.02","name":"Unaaha"},{"code":"74.02.03","name":"Wawotobi"},{"code":"74.02.19","name":"Wonggeduku"},{"code":"74.02.41","name":"Wonggeduku Barat"}],"meta":{"administrative_area_level":3,"updated_at":"2025-07-04"}}